iup/__init__.py
iup/config.py
iup/default_config.py
iup/main.py
iup-0.3.dist-info/METADATA
iup-0.3.dist-info/WHEEL
iup-0.3.dist-info/entry_points.txt
iup-0.3.dist-info/top_level.txt
iup-0.3.dist-info/RECORD
