Metadata-Version: 2.1
Name: iup
Version: 0.3
Summary: ipset updater for openwrt
Author: nobitaqaq
Author-email: xiaoleigs@gmail.com
Keywords: ipset,openwrt
Requires-Python: >=3.8
Requires-Dist: paramiko
